langfuse_pydantic_ai/__init__.py
langfuse_pydantic_ai/_warpper.py
langfuse_pydantic_ai-0.2.1.dist-info/METADATA
langfuse_pydantic_ai-0.2.1.dist-info/WHEEL
langfuse_pydantic_ai-0.2.1.dist-info/licenses/LICENSE
langfuse_pydantic_ai-0.2.1.dist-info/RECORD
